simple_termenu/__init__.py
simple_termenu/simple_termenu.py
simple_termenu-1.0.4.dist-info/LICENSE.rst
simple_termenu-1.0.4.dist-info/METADATA
simple_termenu-1.0.4.dist-info/WHEEL
simple_termenu-1.0.4.dist-info/top_level.txt
simple_termenu-1.0.4.dist-info/RECORD
