Metadata-Version: 2.1
Name: simple-termenu
Version: 1.0.4
Summary: Package for making simple menu in your terminal
Author-email: 72y9op <72y9op@gmail.com>
Project-URL: Homepage, https://github.com/72y9op/simple_termenu
Project-URL: Bug Tracker, https://github.com/72y9op/simple_termenu/issues
Classifier: Programming Language :: Python :: 3
Classifier: License :: OSI Approved :: MIT License
Classifier: Operating System :: OS Independent
Requires-Python: >=3.7
License-File: LICENSE.rst
